{
  "project1": {
    "version": 1483929559352,
    "dev": {
      "_env": "development",
      "_root": "/static/project1/"
    },
    "pro": {
      "_env": "production",
      "_root": "http://qcfile.b0.upaiyun.com/fitness/project1/1483929559352/"
    }
  },
  "project2": {
    "version": 1483929559352,
    "dev": {
      "_env": "development",
      "_root": "/static/project2/"
    },
    "pro": {
      "_env": "production",
      "_root": "http://qcfile.b0.upaiyun.com/fitness/project2/1483929559352/"
    }
  }
}